embreex-2.17.7.post7.dist-info/RECORD
embreex-2.17.7.post7.dist-info/WHEEL
embreex-2.17.7.post7.dist-info/top_level.txt
embreex-2.17.7.post7.dist-info/METADATA
embreex-2.17.7.post7.dist-info/licenses/LICENSE
embreex/rtcore.pxd
embreex/rtcore_scene.cpython-39-darwin.so
embreex/__init__.pxd
embreex/__init__.py
embreex/triangles.cpython-39-darwin.so
embreex/rtcore.cpython-39-darwin.so
embreex/rtcore_geometry_user.pxd
embreex/rtcore_geometry.pxd
embreex/rtcore_scene.pxd
embreex/rtcore_ray.pxd
embreex/mesh_construction.cpython-39-darwin.so
embreex/.dylibs/libembree.2.dylib
embreex/.dylibs/libtbbmalloc.dylib
embreex/.dylibs/libtbb.dylib
