Metadata-Version: 2.1
Name: embreex
Version: 2.17.7.post7
Summary: Python binding for Intel's Embree ray engine
License: Copyright (c) 2015, Anthony Scopatz
Project-URL: Source, https://github.com/trimesh/embreex
Requires-Python: >=3.8
License-File: LICENSE
Requires-Dist: numpy
